{
    "compilerOptions": {
        "package": "@ohos/arkui",
        "outDir": "build/unmemoized/abc",
        "baseUrl": "./build/unmemoized/src",
        "paths": {
            "@ohos/arkui": ["../../../../implementation/build/unmemoized/src"],
            "#components": ["../../../../../arkui/build/unmemoized/src/generated/arkts"],
            "#arkcompat/*": ["../../../../../../arkoala/arkui-common/build/unmemoized/src/arkts/*"],
            "@koalaui/interop": ["../../../../../../interop/src/arkts"],
            "@koalaui/runtime": ["../../../../../../incremental/runtime/build/unmemoized/src"],
            "@koalaui/common": ["../../../../../../incremental/common/src"],
            "@koalaui/compat": ["../../../../../../incremental/compat/src/arkts"],
            "@koalaui/arkui-common": ["../../../../../../arkoala/arkui-common/build/unmemoized/src"],
            "@koalaui/arkts-arkui": ["../../../../../arkui/build/unmemoized/src"]
        }
    },
    "include": ["build/unmemoized/src/**/*.ts", "build/unmemoized/src/*.ts"],
    "references": [
    ]
}
