{
  "string": [
    {
      "name": "module_desc",
      "value": "module description"
    },
    {
      "name": "EntryAbility_desc",
      "value": "description"
    },
    {
      "name": "EntryAbility_label",
      "value": "label"
    },
    {
      "name": "hello_world",
      "value": "Hello World"
    },
    {
      "name": "mytitle",
      "value": "Hello World"
    },
    {
      "name": "image_url",
      "value": "http://p0.meituan.net/content/9543e34f59c343282a8f83926f72f585173498.jpg.webp@289w_289h_1e_1l"
    }
  ]
}